meowdb.py
meowdb-0.1.3.dist-info/METADATA
meowdb-0.1.3.dist-info/WHEEL
meowdb-0.1.3.dist-info/top_level.txt
meowdb-0.1.3.dist-info/RECORD
