Metadata-Version: 2.1
Name: meowdb
Version: 0.1.3
Summary: A Python interface for the MeowDB in-memory database server.
Author-email: FakeCoder01 <fakecoder@duck.com>
License: MIT
Project-URL: Homepage, https://github.com/FakeCoder01/MeowDB
Requires-Python: >=3.6
